chromelogger.py
setup.py
chromelogger.egg-info/PKG-INFO
chromelogger.egg-info/SOURCES.txt
chromelogger.egg-info/dependency_links.txt
chromelogger.egg-info/requires.txt
chromelogger.egg-info/top_level.txt