Metadata-Version: 1.1
Name: chromelogger
Version: 0.4.2
Summary: Python library for logging data to Google Chrome console.
Home-page: https://github.com/ccampbell/chromelogger-python
Author: Craig Campbell
Author-email: iamcraigcampbell@gmail.com
License: Apache 2.0
Download-URL: https://github.com/ccampbell/chromelogger-python/archive/0.4.2.zip#egg=chromelogger-0.4.2
Platform: any
